{

   "files": [   

      {

         "name": "SG-ทรู-เรียนฟรี-True",

         "url": "https://raw.githubusercontent.com/savat88/apiss/main/Free3-TH_Dtac.ovpn"

      },

     {

         "name": "SG-DtacSocial-Digital-VIP",

         "url": "https://raw.githubusercontent.com/savat88/apiss/main/Free2-TH_Dtac.ovpn"

      },

      {

         "name": "SG-TrueSocial-Digital-VIP",

         "url": "https://raw.githubusercontent.com/savat88/apiss/main/Free1-TH_Dtac.ovpn"

      }

   ],

"message":"เทส",

   "title":"New config " ,

   "version": 1.1

}
